pyiplocation/__init__.py
pyiplocation-1.0.dist-info/LICENSE
pyiplocation-1.0.dist-info/METADATA
pyiplocation-1.0.dist-info/WHEEL
pyiplocation-1.0.dist-info/top_level.txt
pyiplocation-1.0.dist-info/RECORD
